{
    "feature": "sex",
    "threshold": 0.6326530612244898,
    "children": {
        "<=": {
            "feature": "slope",
            "threshold": 1.4166666666666667,
            "children": {
                "<=": {
                    "label": 0
                },
                ">": {
                    "feature": "exang",
                    "threshold": 0.25,
                    "children": {
                        "<=": {
                            "label": 0
                        },
                        ">": {
                            "label": 0
                        }
                    }
                }
            }
        },
        ">": {
            "feature": "restecg",
            "threshold": 0.9516129032258065,
            "children": {
                "<=": {
                    "label": 0
                },
                ">": {
                    "label": 0
                }
            }
        }
    }
}