{
    "feature": "ca",
    "threshold": 0.48404255319148937,
    "children": {
        "<=": {
            "label": 0
        },
        ">": {
            "feature": "restecg",
            "threshold": 0.8888888888888888,
            "children": {
                "<=": {
                    "feature": "sex",
                    "threshold": 0.6571428571428571,
                    "children": {
                        "<=": {
                            "label": 0
                        },
                        ">": {
                            "feature": "cp",
                            "threshold": 3.217391304347826,
                            "children": {
                                "<=": {
                                    "label": 0
                                },
                                ">": {
                                    "label": 1
                                }
                            }
                        }
                    }
                },
                ">": {
                    "feature": "trestbps",
                    "threshold": 127.35714285714286,
                    "children": {
                        "<=": {
                            "label": 1
                        },
                        ">": {
                            "feature": "exang",
                            "threshold": 0.23076923076923078,
                            "children": {
                                "<=": {
                                    "label": 1
                                },
                                ">": {
                                    "label": 1
                                }
                            }
                        }
                    }
                }
            }
        }
    }
}